{
"name": "Covers factory",
"description": "Produces combat units -Cover-",
"type": "UnitFactory",
"size": 3,
"consumes": {
"power": 3
},
"plans": [
{
    "unit": "cover-t1",
    	"requirements": [
		{"item": "escar", "amount": 12},
		{"item": "tin", "amount": 10}
     ]
  "time": 1200
  }
  ],
   "requirements": [
	{"item": "kianit", "amount": 125},
	{"item": "tin", "amount": 100},
	{"item": "escar", "amount": 75}
],
"category": "units",
research: {
    parent: TechTree-UnitsCategory
    objectives: [
        {
            type: "OnSector",
            preset: "thelandingsite"
        }
    ]
},
"researchCostMultiplier": 0.5
}